setup.py
pyJsonStorage/__init__.py
pyJsonStorage/package.py
pyJsonStorage.egg-info/PKG-INFO
pyJsonStorage.egg-info/SOURCES.txt
pyJsonStorage.egg-info/dependency_links.txt
pyJsonStorage.egg-info/top_level.txt