Metadata-Version: 2.1
Name: pyJsonStorage
Version: 1.0
Summary: pyJsonStorage is a Python package designed to implement basic database functionalities using JSON (JavaScript Object Notation). This package provides various features such as creating a new database, inserting rows, updating, and deleting rows. It leverages the JSON module from Python's core libraries for managing JSON files.
Home-page: https://github.com/sachin1152207/pyJsonStorage
Author: Sachin Shrivastav
Author-email: sachin@sachinshrivastav.com.np
License: UNKNOWN
Platform: UNKNOWN
